bonjour.py
bonjour-0.0.3.dist-info/DESCRIPTION.rst
bonjour-0.0.3.dist-info/METADATA
bonjour-0.0.3.dist-info/RECORD
bonjour-0.0.3.dist-info/WHEEL
bonjour-0.0.3.dist-info/entry_points.txt
bonjour-0.0.3.dist-info/metadata.json
bonjour-0.0.3.dist-info/top_level.txt
