Metadata-Version: 2.0
Name: bonjour
Version: 0.0.3
Summary: A module / utility to say hello to you in French.
Home-page: https://github.com/Em774/bonjour_monde
Author: Emilie
Author-email: emilie@wegotpop.com
License: MIT
Platform: UNKNOWN
Classifier: Development Status :: 4 - Beta
